kaito_rag_engine_client/__init__.py
kaito_rag_engine_client/client.py
kaito_rag_engine_client/errors.py
kaito_rag_engine_client/py.typed
kaito_rag_engine_client/types.py
kaito_rag_engine_client/api/__init__.py
kaito_rag_engine_client/api/chat/__init__.py
kaito_rag_engine_client/api/chat/chat.py
kaito_rag_engine_client/api/index/__init__.py
kaito_rag_engine_client/api/index/create_index.py
kaito_rag_engine_client/api/index/delete_documents_in_index.py
kaito_rag_engine_client/api/index/delete_index.py
kaito_rag_engine_client/api/index/list_documents_in_index.py
kaito_rag_engine_client/api/index/list_indexes.py
kaito_rag_engine_client/api/index/load_index.py
kaito_rag_engine_client/api/index/persist_index.py
kaito_rag_engine_client/api/index/update_documents_in_index.py
kaito_rag_engine_client/api/monitoring/__init__.py
kaito_rag_engine_client/api/monitoring/get_health.py
kaito_rag_engine_client/api/monitoring/get_metrics.py
kaito_rag_engine_client/models/__init__.py
kaito_rag_engine_client/models/annotation.py
kaito_rag_engine_client/models/annotation_url_citation.py
kaito_rag_engine_client/models/chat_completion_audio.py
kaito_rag_engine_client/models/chat_completion_message.py
kaito_rag_engine_client/models/chat_completion_message_tool_call.py
kaito_rag_engine_client/models/chat_completion_response.py
kaito_rag_engine_client/models/chat_completion_response_service_tier_type_0.py
kaito_rag_engine_client/models/chat_completion_token_logprob.py
kaito_rag_engine_client/models/chat_request.py
kaito_rag_engine_client/models/choice.py
kaito_rag_engine_client/models/choice_finish_reason.py
kaito_rag_engine_client/models/choice_logprobs.py
kaito_rag_engine_client/models/completion_tokens_details.py
kaito_rag_engine_client/models/completion_usage.py
kaito_rag_engine_client/models/delete_document_request.py
kaito_rag_engine_client/models/delete_document_response.py
kaito_rag_engine_client/models/document.py
kaito_rag_engine_client/models/document_metadata_type_0.py
kaito_rag_engine_client-0.7.0.dist-info/licenses/LICENSE
kaito_rag_engine_client-0.7.0.dist-info/METADATA
kaito_rag_engine_client-0.7.0.dist-info/WHEEL
kaito_rag_engine_client-0.7.0.dist-info/top_level.txt
kaito_rag_engine_client-0.7.0.dist-info/RECORD
