Metadata-Version: 2.4
Name: kaito-rag-engine-client
Version: 0.7.0
Summary: KAITO RAG Engine Client
Author-email: Fei Guo <guofei@microsoft.com>, Brandon Foley <brandon.foley@microsoft.com>
License-Expression: Apache-2.0
Project-URL: Homepage, https://github.com/kaito-project/kaito-rag-api
Project-URL: Issues, https://github.com/kaito-project/kaito-rag-api/issues
Classifier: Programming Language :: Python :: 3
Classifier: Operating System :: OS Independent
Requires-Python: >=3.9
License-File: LICENSE
Requires-Dist: httpx>=0.24.0
Requires-Dist: attrs>=21.0.0
Dynamic: license-file
